README.md
setup.py
bqorm/__init__.py
bqorm/conversions.py
bqorm.egg-info/PKG-INFO
bqorm.egg-info/SOURCES.txt
bqorm.egg-info/dependency_links.txt
bqorm.egg-info/requires.txt
bqorm.egg-info/top_level.txt