Metadata-Version: 2.1
Name: bqorm
Version: 0.2.0
Summary: Python Micro-ORM for BigQuery
Home-page: https://github.com/42DIGITAL/bqorm
Author: Jonathan Rahn
Author-email: jonathan.rahn@42digital.de
License: UNKNOWN
Platform: UNKNOWN
Provides-Extra: test
